tldrstory/__init__.py
tldrstory/api.py
tldrstory/app.py
tldrstory/database.py
tldrstory/index.py
tldrstory/sqlite.py
tldrstory/source/__init__.py
tldrstory/source/factory.py
tldrstory/source/reddit.py
tldrstory/source/rss.py
tldrstory/source/source.py
tldrstory-1.4.0.dist-info/LICENSE
tldrstory-1.4.0.dist-info/METADATA
tldrstory-1.4.0.dist-info/WHEEL
tldrstory-1.4.0.dist-info/top_level.txt
tldrstory-1.4.0.dist-info/RECORD
