Metadata-Version: 2.1
Name: tldrstory
Version: 1.4.0
Summary: AI-powered understanding of headlines and story text
Home-page: https://github.com/neuml/tldrstory
Author: NeuML
License: Apache 2.0: http://www.apache.org/licenses/LICENSE-2.0
Project-URL: Documentation, https://github.com/neuml/tldrstory
Project-URL: Issue Tracker, https://github.com/neuml/tldrstory/issues
Project-URL: Source Code, https://github.com/neuml/tldrstory
Keywords: search embedding machine-learning nlp
Platform: UNKNOWN
Classifier: License :: OSI Approved :: Apache Software License
Classifier: Operating System :: OS Independent
Classifier: Programming Language :: Python :: 3
Classifier: Topic :: Scientific/Engineering :: Artificial Intelligence
Classifier: Topic :: Software Development
Classifier: Topic :: Text Processing :: Indexing
Classifier: Topic :: Utilities
Requires-Python: >=3.6
Requires-Dist: croniter (>=0.3.34)
Requires-Dist: feedparser (>=6.0.1)
Requires-Dist: praw (>=7.1.0)
Requires-Dist: requests (>=2.24.0)
Requires-Dist: streamlit (>=0.68.0)
Requires-Dist: txtai[api] (>=3.2.0)
